s3_storage_provider.py
s3_synapse_storage_provider-1.5.3.data/scripts/s3_media_upload
s3_synapse_storage_provider-1.5.3.dist-info/licenses/LICENSE
s3_synapse_storage_provider-1.5.3.dist-info/METADATA
s3_synapse_storage_provider-1.5.3.dist-info/WHEEL
s3_synapse_storage_provider-1.5.3.dist-info/top_level.txt
s3_synapse_storage_provider-1.5.3.dist-info/RECORD
