Metadata-Version: 2.4
Name: s3-synapse-storage-provider
Version: 1.5.3
Summary: A storage provider which can fetch and store media in Amazon S3.
Home-page: https://github.com/elyesbenamor/synapse-s3-storage-provider.git
Author: matrix.org team and contributors
Classifier: Programming Language :: Python :: 3
Classifier: License :: OSI Approved :: Apache Software License
License-File: LICENSE
Requires-Dist: boto3<2.0,>=1.9.23
Requires-Dist: botocore<2.0,>=1.31.62
Requires-Dist: humanize<5.0,>=4.0
Requires-Dist: psycopg2<3.0,>=2.7.5
Requires-Dist: PyYAML<7.0,>=5.4
Requires-Dist: tqdm<5.0,>=4.26.0
Requires-Dist: Twisted
Dynamic: author
Dynamic: classifier
Dynamic: description
Dynamic: description-content-type
Dynamic: home-page
Dynamic: license-file
Dynamic: requires-dist
Dynamic: summary
